ffmpeg_binaries/__init__.py
ffmpeg_binaries/executable.py
ffmpeg_binaries/internals/__init__.py
ffmpeg_binaries/internals/__pyinstaller_hooks/__init__.py
ffmpeg_binaries/internals/__pyinstaller_hooks/hook-ffmpeg.py
ffmpeg_binaries/internals/__pyinstaller_hooks/hook-ffmpeg_binaries.py
ffmpeg_binaries/internals/downloaders/__init__.py
ffmpeg_binaries/internals/downloaders/binaries.json
ffmpeg_binaries/internals/downloaders/binaries_downloader.py
ffmpeg_binaries/internals/downloaders/downloader.py
ffmpeg_binaries/internals/downloaders/mac.py
ffmpeg_binaries/internals/downloaders/nix.py
ffmpeg_binaries/internals/downloaders/win.py
ffmpeg_binaries_compat-1.1.0.dist-info/licenses/LICENSE
ffmpeg_binaries_compat-1.1.0.dist-info/METADATA
ffmpeg_binaries_compat-1.1.0.dist-info/WHEEL
ffmpeg_binaries_compat-1.1.0.dist-info/entry_points.txt
ffmpeg_binaries_compat-1.1.0.dist-info/top_level.txt
ffmpeg_binaries_compat-1.1.0.dist-info/RECORD
