Metadata-Version: 2.4
Name: ffmpeg-binaries-compat
Version: 1.1.0
Summary: A static build of ffmpeg for Python with a custom namespace to avoid conflicts
Author-email: Matteo Dell'Acqua <dellacqua.matteo99@gmail.com>
Maintainer-email: Matteo Dell'Acqua <dellacqua.matteo99@gmail.com>
Project-URL: MyHomepage, https://github.com/MatteoH2O1999/ffmpeg-binaries
Keywords: ffmpeg,static
Classifier: Programming Language :: Python :: 3 :: Only
Classifier: Programming Language :: Python :: 3.9
Classifier: Programming Language :: Python :: 3.10
Classifier: Programming Language :: Python :: 3.11
Classifier: Programming Language :: Python :: 3.12
Classifier: Programming Language :: Python :: 3.13
Requires-Python: >=3.9
License-File: LICENSE
Requires-Dist: requests
Requires-Dist: patool
Dynamic: license-file
